pathlims/__init__.py
pathlims/generators.py
pathlims/limits.py
pathlims-2.0.post1.dist-info/METADATA
pathlims-2.0.post1.dist-info/WHEEL
pathlims-2.0.post1.dist-info/licenses/LICENSE.txt
pathlims-2.0.post1.dist-info/RECORD
