Metadata-Version: 2.4
Name: pathlims
Version: 2.0.post1
Summary: A package to study the limits of pathlength and efficiency of complex networks.
Project-URL: Homepage, https://github.com/gorkazl/PathLims
Project-URL: Source Code, https://github.com/gorkazl/PathLims
Project-URL: Bug Tracker, https://github.com/gorkazl/PathLims/issues
Project-URL: Documentation, https://github.com/gorkazl/PahLims/blob/main/README.md
Author: Romain Brasselet
Author-email: Gorka Zamora-López <gorka@Zamora-Lopez.xyz>
License-Expression: Apache-2.0
License-File: LICENSE.txt
Keywords: complex networks,graph theory,network analysis
Classifier: Development Status :: 5 - Production/Stable
Classifier: Intended Audience :: Developers
Classifier: Intended Audience :: Education
Classifier: Intended Audience :: Science/Research
Classifier: License :: OSI Approved :: Apache Software License
Classifier: Operating System :: OS Independent
Classifier: Programming Language :: Python
Classifier: Programming Language :: Python :: 3 :: Only
Classifier: Topic :: Scientific/Engineering :: Bio-Informatics
Classifier: Topic :: Scientific/Engineering :: Information Analysis
Classifier: Topic :: Scientific/Engineering :: Mathematics
Classifier: Topic :: Scientific/Engineering :: Physics
Classifier: Topic :: Software Development :: Libraries :: Python Modules
Requires-Dist: numpy>=1.6
Requires-Dist: scipy
